lutron_leap_cli/__init__.py
lutron_leap_cli/main.py
lutron_leap_cli/commands/__init__.py
lutron_leap_cli/commands/discover.py
lutron_leap_cli/commands/pair.py
lutron_leap_cli/commands/rooms.py
lutron_leap_cli/commands/scenes.py
lutron_leap_cli/commands/watch.py
lutron_leap_cli/commands/zones.py
lutron_leap_cli/core/__init__.py
lutron_leap_cli/core/bridge.py
lutron_leap_cli/core/buttons.py
lutron_leap_cli/core/cache.py
lutron_leap_cli/core/config.py
lutron_leap_cli/core/models.py
lutron_leap_cli/core/scenes.py
lutron_leap_cli/output/__init__.py
lutron_leap_cli/output/formatter.py
lutron_leap_cli/output/tables.py
lutron_leap_cli-0.1.11.dist-info/METADATA
lutron_leap_cli-0.1.11.dist-info/WHEEL
lutron_leap_cli-0.1.11.dist-info/entry_points.txt
lutron_leap_cli-0.1.11.dist-info/RECORD
