Metadata-Version: 2.4
Name: lutron-leap-cli
Version: 0.1.11
Summary: CLI tool for controlling Lutron lighting systems via LEAP protocol (Caseta, RA2 Select, RadioRA3, HomeWorks QSX)
Project-URL: Homepage, https://github.com/peterengelbrecht/lutron-leap-cli
Project-URL: Repository, https://github.com/peterengelbrecht/lutron-leap-cli
Project-URL: Issues, https://github.com/peterengelbrecht/lutron-leap-cli/issues
Author: Peter Engelbrecht
License-Expression: MIT
Keywords: caseta,cli,homeworks,leap,lighting,lutron,smart-home
Classifier: Development Status :: 4 - Beta
Classifier: Environment :: Console
Classifier: Intended Audience :: Developers
Classifier: Intended Audience :: End Users/Desktop
Classifier: License :: OSI Approved :: MIT License
Classifier: Operating System :: OS Independent
Classifier: Programming Language :: Python :: 3
Classifier: Programming Language :: Python :: 3.10
Classifier: Programming Language :: Python :: 3.11
Classifier: Programming Language :: Python :: 3.12
Classifier: Programming Language :: Python :: 3.13
Classifier: Topic :: Home Automation
Requires-Python: >=3.10
Requires-Dist: platformdirs>=4.0.0
Requires-Dist: pydantic>=2.0.0
Requires-Dist: pylutron-caseta>=0.21.0
Requires-Dist: pyyaml>=6.0.0
Requires-Dist: rich>=13.0.0
Requires-Dist: typer>=0.9.0
Provides-Extra: dev
Requires-Dist: ruff>=0.8.0; extra == 'dev'
